{"v":"4.8.0","meta":{"g":"LottieFiles AE 3.5.4","a":"","k":"","d":"","tc":""},"fr":24,"ip":0,"op":48,"w":618,"h":618,"nm":"Fast Food Delivery-04","ddd":0,"assets":[],"layers":[{"ddd":0,"ind":1,"ty":4,"nm":"Layer 3 Outlines","parent":2,"sr":1,"ks":{"o":{"a":1,"k":[{"i":{"x":[0.833],"y":[0.833]},"o":{"x":[0.167],"y":[0.167]},"t":8,"s":[0]},{"i":{"x":[0.833],"y":[0.833]},"o":{"x":[0.167],"y":[0.167]},"t":12,"s":[100]},{"i":{"x":[0.833],"y":[0.833]},"o":{"x":[0.167],"y":[0.167]},"t":36,"s":[100]},{"t":40,"s":[0]}],"ix":11},"r":{"a":1,"k":[{"i":{"x":[0.667],"y":[1]},"o":{"x":[0.333],"y":[0]},"t":0,"s":[33.588]},{"i":{"x":[0.667],"y":[1]},"o":{"x":[0.333],"y":[0]},"t":4,"s":[32.861]},{"i":{"x":[0.667],"y":[1]},"o":{"x":[0.333],"y":[0]},"t":16,"s":[-9.877]},{"i":{"x":[0.667],"y":[1]},"o":{"x":[0.333],"y":[0]},"t":32,"s":[-9.877]},{"i":{"x":[0.667],"y":[1]},"o":{"x":[0.333],"y":[0]},"t":44,"s":[32.861]},{"t":47,"s":[33.588]}],"ix":10},"p":{"a":0,"k":[402.688,293.44,0],"ix":2},"a":{"a":0,"k":[46.024,304.076,0],"ix":1},"s":{"a":1,"k":[{"i":{"x":[0.667,0.667,0.667],"y":[1,1,1]},"o":{"x":[0.333,0.333,0.333],"y":[0,0,0]},"t":8,"s":[71,71,100]},{"i":{"x":[0.667,0.667,0.667],"y":[1,1,1]},"o":{"x":[0.333,0.333,0.333],"y":[0,0,0]},"t":20,"s":[100,100,100]},{"i":{"x":[0.667,0.667,0.667],"y":[1,1,1]},"o":{"x":[0.333,0.333,0.333],"y":[0,0,0]},"t":28,"s":[100,100,100]},{"t":40,"s":[71,71,100]}],"ix":6}},"ao":0,"shapes":[{"ty":"gr","it":[{"ind":0,"ty":"sh","ix":1,"ks":{"a":0,"k":{"i":[[0,0],[0,0]],"o":[[0,0],[0,0]],"v":[[165.867,89.842],[187.119,89.842]],"c":false},"ix":2},"nm":"Path 1","mn":"ADBE Vector Shape - Group","hd":false},{"ty":"st","c":{"a":0,"k":[0.952327713312,0.863649495443,0.080325998044,1],"ix":3},"o":{"a":0,"k":100,"ix":4},"w":{"a":0,"k":5.447,"ix":5},"lc":2,"lj":2,"bm":0,"nm":"Stroke 1","mn":"ADBE Vector Graphic - Stroke","hd":false},{"ty":"tr","p":{"a":0,"k":[0,0],"ix":2},"a":{"a":0,"k":[0,0],"ix":1},"s":{"a":0,"k":[100,100],"ix":3},"r":{"a":0,"k":0,"ix":6},"o":{"a":0,"k":100,"ix":7},"sk":{"a":0,"k":0,"ix":4},"sa":{"a":0,"k":0,"ix":5},"nm":"Transform"}],"nm":"Group 1","np":2,"cix":2,"bm":0,"ix":1,"mn":"ADBE Vector Group","hd":false},{"ty":"gr","it":[{"ind":0,"ty":"sh","ix":1,"ks":{"a":0,"k":{"i":[[0,0],[0,0]],"o":[[0,0],[0,0]],"v":[[190.454,64.962],[190.454,110.545]],"c":false},"ix":2},"nm":"Path 1","mn":"ADBE Vector Shape - Group","hd":false},{"ty":"st","c":{"a":0,"k":[0.952327713312,0.863649495443,0.080325998044,1],"ix":3},"o":{"a":0,"k":100,"ix":4},"w":{"a":0,"k":5.447,"ix":5},"lc":2,"lj":2,"bm":0,"nm":"Stroke 1","mn":"ADBE Vector Graphic - Stroke","hd":false},{"ty":"tr","p":{"a":0,"k":[0,0],"ix":2},"a":{"a":0,"k":[0,0],"ix":1},"s":{"a":0,"k":[100,100],"ix":3},"r":{"a":0,"k":0,"ix":6},"o":{"a":0,"k":100,"ix":7},"sk":{"a":0,"k":0,"ix":4},"sa":{"a":0,"k":0,"ix":5},"nm":"Transform"}],"nm":"Group 2","np":2,"cix":2,"bm":0,"ix":2,"mn":"ADBE Vector Group","hd":false},{"ty":"gr","it":[{"ind":0,"ty":"sh","ix":1,"ks":{"a":0,"k":{"i":[[0,0],[0,0]],"o":[[0,0],[0,0]],"v":[[165.867,64.962],[165.867,110.545]],"c":false},"ix":2},"nm":"Path 1","mn":"ADBE Vector Shape - Group","hd":false},{"ty":"st","c":{"a":0,"k":[0.952327713312,0.863649495443,0.080325998044,1],"ix":3},"o":{"a":0,"k":100,"ix":4},"w":{"a":0,"k":5.447,"ix":5},"lc":2,"lj":2,"bm":0,"nm":"Stroke 1","mn":"ADBE Vector Graphic - Stroke","hd":false},{"ty":"tr","p":{"a":0,"k":[0,0],"ix":2},"a":{"a":0,"k":[0,0],"ix":1},"s":{"a":0,"k":[100,100],"ix":3},"r":{"a":0,"k":0,"ix":6},"o":{"a":0,"k":100,"ix":7},"sk":{"a":0,"k":0,"ix":4},"sa":{"a":0,"k":0,"ix":5},"nm":"Transform"}],"nm":"Group 3","np":2,"cix":2,"bm":0,"ix":3,"mn":"ADBE Vector Group","hd":false},{"ty":"gr","it":[{"ind":0,"ty":"sh","ix":1,"ks":{"a":0,"k":{"i":[[0,0],[0.053,-32.65]],"o":[[-0.053,32.649],[0,0]],"v":[[0.08,-48.974],[-0.08,48.974]],"c":false},"ix":2},"nm":"Path 1","mn":"ADBE Vector Shape - Group","hd":false},{"ty":"st","c":{"a":0,"k":[0.952327713312,0.863649495443,0.080325998044,1],"ix":3},"o":{"a":0,"k":100,"ix":4},"w":{"a":0,"k":9.507,"ix":5},"lc":2,"lj":2,"bm":0,"nm":"Stroke 1","mn":"ADBE Vector Graphic - Stroke","hd":false},{"ty":"tr","p":{"a":0,"k":[147.276,122.357],"ix":2},"a":{"a":0,"k":[0,0],"ix":1},"s":{"a":0,"k":[100,100],"ix":3},"r":{"a":0,"k":0,"ix":6},"o":{"a":0,"k":100,"ix":7},"sk":{"a":0,"k":0,"ix":4},"sa":{"a":0,"k":0,"ix":5},"nm":"Transform"}],"nm":"Group 4","np":2,"cix":2,"bm":0,"ix":4,"mn":"ADBE Vector Group","hd":false},{"ty":"gr","it":[{"ind":0,"ty":"sh","ix":1,"ks":{"a":0,"k":{"i":[[0,0],[11.476,-13.701],[0,0],[-20.065,0.191]],"o":[[-11.475,13.701],[0,0],[20.065,-0.191],[0,0]],"v":[[4.329,-23.486],[-30.098,17.618],[-30.098,23.486],[30.098,22.913]],"c":false},"ix":2},"nm":"Path 1","mn":"ADBE Vector Shape - Group","hd":false},{"ty":"st","c":{"a":0,"k":[0.952327713312,0.863649495443,0.080325998044,1],"ix":3},"o":{"a":0,"k":100,"ix":4},"w":{"a":0,"k":9.507,"ix":5},"lc":2,"lj":2,"bm":0,"nm":"Stroke 1","mn":"ADBE Vector Graphic - Stroke","hd":false},{"ty":"tr","p":{"a":0,"k":[143.026,96.869],"ix":2},"a":{"a":0,"k":[0,0],"ix":1},"s":{"a":0,"k":[100,100],"ix":3},"r":{"a":0,"k":0,"ix":6},"o":{"a":0,"k":100,"ix":7},"sk":{"a":0,"k":0,"ix":4},"sa":{"a":0,"k":0,"ix":5},"nm":"Transform"}],"nm":"Group 5","np":2,"cix":2,"bm":0,"ix":5,"mn":"ADBE Vector Group","hd":false},{"ty":"gr","it":[{"ind":0,"ty":"sh","ix":1,"ks":{"a":0,"k":{"i":[[0,0],[-13.986,-0.749],[4.165,-19.042],[8.769,-5.889],[6.419,-5.903],[0.075,-2.386],[0,0]],"o":[[0.19,-17.927],[15.079,0.808],[-7.451,3.585],[-9.397,6.311],[-0.074,2.387],[0,0],[0,0]],"v":[[-30.467,-7.686],[-1.607,-37.904],[23.178,-1.234],[-1.396,12.833],[-25.069,31.492],[-25.293,38.652],[30.467,38.652]],"c":false},"ix":2},"nm":"Path 1","mn":"ADBE Vector Shape - Group","hd":false},{"ty":"st","c":{"a":0,"k":[0.952327713312,0.863649495443,0.080325998044,1],"ix":3},"o":{"a":0,"k":100,"ix":4},"w":{"a":0,"k":9.507,"ix":5},"lc":2,"lj":2,"bm":0,"nm":"Stroke 1","mn":"ADBE Vector Graphic - Stroke","hd":false},{"ty":"tr","p":{"a":0,"k":[74.781,120.781],"ix":2},"a":{"a":0,"k":[0,0],"ix":1},"s":{"a":0,"k":[100,100],"ix":3},"r":{"a":0,"k":0,"ix":6},"o":{"a":0,"k":100,"ix":7},"sk":{"a":0,"k":0,"ix":4},"sa":{"a":0,"k":0,"ix":5},"nm":"Transform"}],"nm":"Group 6","np":2,"cix":2,"bm":0,"ix":6,"mn":"ADBE Vector Group","hd":false},{"ty":"gr","it":[{"ind":0,"ty":"sh","ix":1,"ks":{"a":0,"k":{"i":[[0,41.458],[56.805,0],[0,-56.804],[-11.67,-16.682],[0.157,0.229],[-1.041,-25.06],[-7.91,-3.413],[-29.75,26.565],[-17.292,8.207],[0.523,-0.239]],"o":[[0,-56.804],[-56.804,0],[0,21.904],[-0.187,-0.269],[2.658,12.813],[1.725,41.516],[8.621,3.72],[24.826,-22.169],[-0.396,0.189],[35.336,-16.279]],"v":[[102.854,-42.294],[-0.001,-145.148],[-102.854,-42.294],[-84.331,16.593],[-84.851,15.843],[-77.68,73.945],[-74.33,141.428],[-22.161,94.525],[44.377,50.517],[42.986,51.166]],"c":true},"ix":2},"nm":"Path 1","mn":"ADBE Vector Shape - Group","hd":false},{"ty":"st","c":{"a":0,"k":[0.145098039216,0.149019607843,0.411764735802,1],"ix":3},"o":{"a":0,"k":100,"ix":4},"w":{"a":0,"k":7,"ix":5},"lc":1,"lj":1,"ml":10,"bm":0,"nm":"Stroke 1","mn":"ADBE Vector Graphic - Stroke","hd":false},{"ty":"fl","c":{"a":0,"k":[0.8429502001,0,0.302861322141,1],"ix":4},"o":{"a":0,"k":100,"ix":5},"r":1,"bm":0,"nm":"Fill 1","mn":"ADBE Vector Graphic - Fill","hd":false},{"ty":"tr","p":{"a":0,"k":[120.354,162.648],"ix":2},"a":{"a":0,"k":[0,0],"ix":1},"s":{"a":0,"k":[100,100],"ix":3},"r":{"a":0,"k":0,"ix":6},"o":{"a":0,"k":100,"ix":7},"sk":{"a":0,"k":0,"ix":4},"sa":{"a":0,"k":0,"ix":5},"nm":"Transform"}],"nm":"Group 7","np":3,"cix":2,"bm":0,"ix":7,"mn":"ADBE Vector Group","hd":false}],"ip":0,"op":48,"st":0,"bm":0},{"ddd":0,"ind":2,"ty":4,"nm":"Layer 2 Outlines","sr":1,"ks":{"o":{"a":0,"k":100,"ix":11},"r":{"a":1,"k":[{"i":{"x":[0.667],"y":[1]},"o":{"x":[0.333],"y":[0]},"t":2,"s":[12.102]},{"i":{"x":[0.667],"y":[1]},"o":{"x":[0.333],"y":[0]},"t":16,"s":[0]},{"i":{"x":[0.667],"y":[1]},"o":{"x":[0.333],"y":[0]},"t":23,"s":[-2.195]},{"i":{"x":[0.667],"y":[1]},"o":{"x":[0.333],"y":[0]},"t":25,"s":[-2.195]},{"i":{"x":[0.667],"y":[1]},"o":{"x":[0.333],"y":[0]},"t":32,"s":[0]},{"t":46,"s":[12.102]}],"ix":10},"p":{"a":1,"k":[{"i":{"x":0.833,"y":0.833},"o":{"x":0.167,"y":0.167},"t":0,"s":[213.343,337.975,0],"to":[0,0,0],"ti":[0,0,0]},{"t":20,"s":[213.343,337.975,0]}],"ix":2},"a":{"a":0,"k":[198.357,255.12,0],"ix":1},"s":{"a":1,"k":[{"i":{"x":[0.667,0.667,0.667],"y":[1,1,1]},"o":{"x":[0.333,0.333,0.333],"y":[0,0,0]},"t":2,"s":[89,89,100]},{"i":{"x":[0.667,0.667,0.667],"y":[1,1,1]},"o":{"x":[0.333,0.333,0.333],"y":[0,0,0]},"t":16,"s":[100,100,100]},{"i":{"x":[0.667,0.667,0.667],"y":[1,1,1]},"o":{"x":[0.333,0.333,0.333],"y":[0,0,0]},"t":32,"s":[100,100,100]},{"t":46,"s":[89,89,100]}],"ix":6}},"ao":0,"shapes":[{"ty":"gr","it":[{"ind":0,"ty":"sh","ix":1,"ks":{"a":0,"k":{"i":[[-12.602,-16.3],[0,0],[14.3,-11.056],[12.602,16.3],[0,0],[-14.3,11.056]],"o":[[0,0],[12.602,16.3],[-14.3,11.056],[0,0],[-12.602,-16.3],[14.3,-11.055]],"v":[[-7.055,-62.633],[58.839,22.596],[55.765,72.128],[7.055,62.632],[-58.839,-22.596],[-55.765,-72.128]],"c":true},"ix":2},"nm":"Path 1","mn":"ADBE Vector Shape - Group","hd":false},{"ty":"st","c":{"a":0,"k":[0.145098039216,0.149019607843,0.411764735802,1],"ix":3},"o":{"a":0,"k":100,"ix":4},"w":{"a":0,"k":7,"ix":5},"lc":2,"lj":2,"bm":0,"nm":"Stroke 1","mn":"ADBE Vector Graphic - Stroke","hd":false},{"ty":"fl","c":{"a":0,"k":[0,0.437954741833,0.566227153703,1],"ix":4},"o":{"a":0,"k":100,"ix":5},"r":1,"bm":0,"nm":"Fill 1","mn":"ADBE Vector Graphic - Fill","hd":false},{"ty":"tr","p":{"a":0,"k":[158.787,100.684],"ix":2},"a":{"a":0,"k":[0,0],"ix":1},"s":{"a":0,"k":[100,100],"ix":3},"r":{"a":0,"k":0,"ix":6},"o":{"a":0,"k":100,"ix":7},"sk":{"a":0,"k":0,"ix":4},"sa":{"a":0,"k":0,"ix":5},"nm":"Transform"}],"nm":"Group 1","np":3,"cix":2,"bm":0,"ix":1,"mn":"ADBE Vector Group","hd":false},{"ty":"gr","it":[{"ind":0,"ty":"sh","ix":1,"ks":{"a":0,"k":{"i":[[-12.602,-16.3],[0,0],[14.3,-11.056],[12.602,16.3],[0,0],[-14.3,11.056]],"o":[[0,0],[12.602,16.3],[-14.3,11.056],[0,0],[-12.602,-16.3],[14.3,-11.055]],"v":[[-7.055,-62.633],[58.839,22.596],[55.765,72.127],[7.055,62.632],[-58.839,-22.596],[-55.765,-72.129]],"c":true},"ix":2},"nm":"Path 1","mn":"ADBE Vector Shape - Group","hd":false},{"ty":"st","c":{"a":0,"k":[0.145098039216,0.149019607843,0.411764735802,1],"ix":3},"o":{"a":0,"k":100,"ix":4},"w":{"a":0,"k":7,"ix":5},"lc":2,"lj":2,"bm":0,"nm":"Stroke 1","mn":"ADBE Vector Graphic - Stroke","hd":false},{"ty":"fl","c":{"a":0,"k":[0,0.437954741833,0.566227153703,1],"ix":4},"o":{"a":0,"k":100,"ix":5},"r":1,"bm":0,"nm":"Fill 1","mn":"ADBE Vector Graphic - Fill","hd":false},{"ty":"tr","p":{"a":0,"k":[344.734,341.192],"ix":2},"a":{"a":0,"k":[0,0],"ix":1},"s":{"a":0,"k":[100,100],"ix":3},"r":{"a":0,"k":0,"ix":6},"o":{"a":0,"k":100,"ix":7},"sk":{"a":0,"k":0,"ix":4},"sa":{"a":0,"k":0,"ix":5},"nm":"Transform"}],"nm":"Group 2","np":3,"cix":2,"bm":0,"ix":2,"mn":"ADBE Vector Group","hd":false},{"ty":"gr","it":[{"ind":0,"ty":"sh","ix":1,"ks":{"a":0,"k":{"i":[[0.698,-0.54],[0,0],[-1.694,-2.192],[0,0],[-2.192,1.694],[0,0],[0.539,0.698],[-0.698,0.539],[0,0],[-0.539,-0.698],[0,0],[0.698,-0.54],[0,0],[31.91,41.274],[0,0],[-41.273,31.911],[0,0],[-0.54,-0.697],[0,0],[0.698,-0.54],[0,0],[0.539,0.698],[0,0]],"o":[[0,0],[-2.191,1.694],[0,0],[1.694,2.191],[0,0],[0.698,-0.539],[-0.54,-0.698],[0,0],[0.698,-0.539],[0,0],[0.539,0.698],[0,0],[-41.274,31.911],[0,0],[-31.91,-41.273],[0,0],[0.698,-0.54],[0,0],[0.54,0.698],[0,0],[-0.698,0.54],[0,0],[-0.54,-0.698]],"v":[[-29.079,-101.423],[-55.47,-81.019],[-56.37,-73.983],[58.466,74.549],[65.503,75.449],[91.893,55.045],[92.18,52.805],[92.466,50.564],[115.041,33.11],[117.281,33.397],[182.771,118.103],[182.484,120.344],[115.771,171.922],[-16.74,154.968],[-151.4,-19.204],[-134.446,-151.715],[-67.732,-203.293],[-65.492,-203.007],[0.587,-117.538],[0.301,-115.297],[-22.273,-97.844],[-24.514,-98.13],[-26.838,-101.136]],"c":true},"ix":2},"nm":"Path 1","mn":"ADBE Vector Shape - Group","hd":false},{"ty":"st","c":{"a":0,"k":[0.145098039216,0.149019607843,0.411764735802,1],"ix":3},"o":{"a":0,"k":100,"ix":4},"w":{"a":0,"k":7,"ix":5},"lc":2,"lj":2,"bm":0,"nm":"Stroke 1","mn":"ADBE Vector Graphic - Stroke","hd":false},{"ty":"fl","c":{"a":0,"k":[0.596243884517,0.598704738243,0.605090451708,1],"ix":4},"o":{"a":0,"k":100,"ix":5},"r":1,"bm":0,"nm":"Fill 1","mn":"ADBE Vector Graphic - Fill","hd":false},{"ty":"tr","p":{"a":0,"k":[200.81,259.365],"ix":2},"a":{"a":0,"k":[0,0],"ix":1},"s":{"a":0,"k":[100,100],"ix":3},"r":{"a":0,"k":0,"ix":6},"o":{"a":0,"k":100,"ix":7},"sk":{"a":0,"k":0,"ix":4},"sa":{"a":0,"k":0,"ix":5},"nm":"Transform"}],"nm":"Group 3","np":3,"cix":2,"bm":0,"ix":3,"mn":"ADBE Vector Group","hd":false}],"ip":0,"op":48,"st":0,"bm":0}],"markers":[]}